Metadata-Version: 2.1
Name: pipe2codeblock
Version: 1.0.0
Summary: Pipe text into a code block in a markdown file.
Home-page: https://github.com/clbarnes/pipe2codeblock
Author: Chris L. Barnes
Author-email: barnesc@janelia.hhmi.org
License: MIT
Platform: UNKNOWN
Requires-Python: >=3.4
